{
  "header": {
    "uuid": "aaaa1234-1a2b-3c4d-5e6f-000000000002",
    "schema_id": {
      "name": "blood-pressure",
      "version": "4.0",
      "namespace": "omh"
    },
    "source_creation_date_time": "2025-01-01T01:02:01-08:00",
    "modality": "sensed",
    "external_datasheets": [
      {
        "datasheet_type": "manufacturer",
        "datasheet_reference": "iHealth"
      }
    ]
  },
  "body": {
    "systolic_blood_pressure": {
      "value": 115,
      "unit": "mmHg"
    },
    "diastolic_blood_pressure": {
      "value": 60,
      "unit": "mmHg"
    },
    "effective_time_frame": {
      "date_time": "2025-01-01T00:02:00-08:00"
    }
  }
}
