{
  "resourceType" : "StructureMap",
  "id" : "DomainResource4to5",
  "url" : "http://hl7.org/fhir/uv/xver/StructureMap/DomainResource4to5",
  "name" : "DomainResource4to5",
  "title" : "DomainResource Transforms: R4 to R5",
  "status" : "active",
  "description" : "DomainResource Transforms: R4 to R5",
  "structure" : [{
    "url" : "http://hl7.org/fhir/4.0/StructureDefinition/DomainResource",
    "mode" : "source",
    "alias" : "DomainResourceR4"
  },
  {
    "url" : "http://hl7.org/fhir/5.0/StructureDefinition/DomainResource",
    "mode" : "target",
    "alias" : "DomainResourceR5"
  }],
  "import" : ["http://hl7.org/fhir/uv/xver/StructureMap/*4to5"],
  "group" : [{
    "name" : "DomainResource",
    "extends" : "Resource",
    "typeMode" : "type-and-types",
    "input" : [{
      "name" : "src",
      "type" : "DomainResourceR4",
      "mode" : "source"
    },
    {
      "name" : "tgt",
      "type" : "DomainResourceR5",
      "mode" : "target"
    }],
    "rule" : [{
      "name" : "text",
      "source" : [{
        "context" : "src",
        "element" : "text",
        "variable" : "vvv"
      }],
      "target" : [{
        "context" : "tgt",
        "element" : "text",
        "variable" : "vvv",
        "transform" : "create"
      }]
    },
    {
      "name" : "containedResource",
      "source" : [{
        "context" : "src",
        "element" : "contained",
        "variable" : "vvv"
      }],
      "target" : [{
        "context" : "tgt",
        "element" : "contained",
        "variable" : "vvv",
        "transform" : "create"
      }]
    },
    {
      "name" : "extension",
      "source" : [{
        "context" : "src",
        "element" : "extension",
        "variable" : "vvv"
      }],
      "target" : [{
        "context" : "tgt",
        "element" : "extension",
        "variable" : "vvv",
        "transform" : "create"
      }]
    },
    {
      "name" : "modifierExtension",
      "source" : [{
        "context" : "src",
        "element" : "modifierExtension",
        "variable" : "vvv"
      }],
      "target" : [{
        "context" : "tgt",
        "element" : "modifierExtension",
        "variable" : "vvv",
        "transform" : "create"
      }]
    }]
  }]
}
